ppad/__init__.py
ppad/__main__.py
ppad/lib/__init__.py
ppad/lib/util.py
ppad-0.0.11.dist-info/LICENSE
ppad-0.0.11.dist-info/METADATA
ppad-0.0.11.dist-info/WHEEL
ppad-0.0.11.dist-info/entry_points.txt
ppad-0.0.11.dist-info/top_level.txt
ppad-0.0.11.dist-info/RECORD
