Metadata-Version: 2.1
Name: ppad
Version: 0.0.11
Summary: Papertrail log archives downloader
Home-page: https://github.com/nao0x2c6/ppad
Author: Nao Ueda
Author-email: nao.uedder@gmail.com
License: UNKNOWN
Keywords: papertrail
Platform: UNKNOWN
Classifier: License :: OSI Approved :: GNU General Public License v2 (GPLv2)
Classifier: Programming Language :: Python :: 3.9
Requires-Dist: progressbar2 (>=3)
Requires-Dist: python-dateutil (>=2)
Requires-Dist: pytz (>=2020)
Requires-Dist: requests (>=2)
